quart_schema-0.22.0.dist-info/METADATA
quart_schema-0.22.0.dist-info/WHEEL
quart_schema-0.22.0.dist-info/entry_points.txt
quart_schema-0.22.0.dist-info/licenses/LICENSE
quart_schema/__init__.py
quart_schema/conversion.py
quart_schema/documentation.py
quart_schema/extension.py
quart_schema/mixins.py
quart_schema/openapi.py
quart_schema/py.typed
quart_schema/pydantic.py
quart_schema/typing.py
quart_schema/validation.py
quart_schema-0.22.0.dist-info/RECORD
