Metadata-Version: 2.1
Name: quart-schema
Version: 0.22.0
Summary: A Quart extension to provide schema validation
Author-Email: pgjones <philip.graham.jones@googlemail.com>
License: MIT
Classifier: Development Status :: 3 - Alpha
Classifier: Environment :: Web Environment
Classifier: Intended Audience :: Developers
Classifier: License :: OSI Approved :: MIT License
Classifier: Operating System :: OS Independent
Classifier: Programming Language :: Python
Classifier: Programming Language :: Python :: 3
Classifier: Programming Language :: Python :: 3.9
Classifier: Programming Language :: Python :: 3.10
Classifier: Programming Language :: Python :: 3.11
Classifier: Programming Language :: Python :: 3.12
Classifier: Programming Language :: Python :: 3.13
Classifier: Topic :: Internet :: WWW/HTTP :: Dynamic Content
Classifier: Topic :: Software Development :: Libraries :: Python Modules
Requires-Python: >=3.9
Requires-Dist: pyhumps>=1.6.1
Requires-Dist: quart>=0.19.0
Requires-Dist: typing_extensions; python_version < "3.11"
Provides-Extra: docs
Requires-Dist: pydata_sphinx_theme; extra == "docs"
Requires-Dist: sphinx-tabs>=3.4.4; extra == "docs"
Provides-Extra: msgspec
Requires-Dist: msgspec>=0.18; extra == "msgspec"
Provides-Extra: pydantic
Requires-Dist: pydantic>=2; extra == "pydantic"
